spacy_thai/__init__.py
spacy_thai/spacy_thai.py
spacy_thai/ud-thai.udpipe
spacy_thai-0.7.8.dist-info/LICENSE.txt
spacy_thai-0.7.8.dist-info/METADATA
spacy_thai-0.7.8.dist-info/WHEEL
spacy_thai-0.7.8.dist-info/top_level.txt
spacy_thai-0.7.8.dist-info/RECORD
