Metadata-Version: 2.1
Name: spacy-thai
Version: 0.7.8
Summary: Dependency-parser for Thai language
Home-page: https://github.com/KoichiYasuoka/spaCy-Thai
Author: Koichi Yasuoka
Author-email: yasuoka@kanji.zinbun.kyoto-u.ac.jp
License: MIT
Project-URL: Source, https://github.com/KoichiYasuoka/spaCy-Thai
Project-URL: Tracker, https://github.com/KoichiYasuoka/spaCy-Thai/issues
Keywords: spaCy udpipe nlp
Classifier: License :: OSI Approved :: MIT License
Classifier: Programming Language :: Python :: 3
Classifier: Operating System :: POSIX :: Linux
Classifier: Topic :: Text Processing :: Linguistic
Classifier: Natural Language :: Thai
Requires-Python: >=3.6
License-File: LICENSE.txt
Requires-Dist: deplacy (>=2.1.0)
Requires-Dist: pythainlp (>=2.3.2)
Requires-Dist: spacy (>=2.2.2)
Requires-Dist: ufal.udpipe (>=1.2.0)
